aind_behavior_vr_foraging_curricula/__init__.py
aind_behavior_vr_foraging_curricula/cli.py
aind_behavior_vr_foraging_curricula/depletion/__init__.py
aind_behavior_vr_foraging_curricula/depletion/curriculum.py
aind_behavior_vr_foraging_curricula/depletion/helpers.py
aind_behavior_vr_foraging_curricula/depletion/metrics.py
aind_behavior_vr_foraging_curricula/depletion/policies.py
aind_behavior_vr_foraging_curricula/depletion/stages.py
aind_behavior_vr_foraging_curricula/single_site_matching/__init__.py
aind_behavior_vr_foraging_curricula/single_site_matching/curriculum.py
aind_behavior_vr_foraging_curricula/single_site_matching/helpers.py
aind_behavior_vr_foraging_curricula/single_site_matching/metrics.py
aind_behavior_vr_foraging_curricula/single_site_matching/policies.py
aind_behavior_vr_foraging_curricula/single_site_matching/stages.py
aind_behavior_vr_foraging_curricula/template/__init__.py
aind_behavior_vr_foraging_curricula/template/__test_placeholder.py
aind_behavior_vr_foraging_curricula/template/curriculum.py
aind_behavior_vr_foraging_curricula/template/metrics.py
aind_behavior_vr_foraging_curricula/template/stages.py
aind_behavior_vr_foraging_curricula-0.0.1.dist-info/WHEEL
aind_behavior_vr_foraging_curricula-0.0.1.dist-info/entry_points.txt
aind_behavior_vr_foraging_curricula-0.0.1.dist-info/METADATA
aind_behavior_vr_foraging_curricula-0.0.1.dist-info/RECORD
