Metadata-Version: 2.4
Name: aind-behavior-vr-foraging-curricula
Version: 0.0.1
Summary: A library of curricula for the VrForaging task.
Author: Bruno Cruz, Tiffany Ona
Author-email: Bruno Cruz <bruno.cruz@alleninstitute.org>, Tiffany Ona <tiffany.ona@alleninstitute.org>
License-Expression: MIT
Classifier: Programming Language :: Python :: 3.11
Classifier: Programming Language :: Python :: 3.12
Classifier: Programming Language :: Python :: 3.13
Classifier: Operating System :: Microsoft :: Windows
Requires-Dist: aind-behavior-vr-foraging[data]
Requires-Dist: aind-behavior-curriculum
Requires-Dist: pydantic-settings
Requires-Python: >=3.11
Project-URL: Changelog, https://github.com/AllenNeuralDynamics/Aind.Behavior.VrForaging.Curricula/releases
Project-URL: Documentation, https://allenneuraldynamics.github.io/Aind.Behavior.VrForaging.Curricula/
Project-URL: Issues, https://github.com/AllenNeuralDynamics/Aind.Behavior.VrForaging.Curricula/issues
Project-URL: Repository, https://github.com/AllenNeuralDynamics/Aind.Behavior.VrForaging.Curricula/
